class_interference/__init__.py
class_interference/extension.py
class_interference/py.typed
class_interference/version.py
class_interference-1.1.1.dist-info/LICENSE
class_interference-1.1.1.dist-info/METADATA
class_interference-1.1.1.dist-info/WHEEL
class_interference-1.1.1.dist-info/RECORD
