Metadata-Version: 2.1
Name: class-interference
Version: 1.1.1
Summary: Monkey patching utilities for classes
Home-page: https://github.com/reartnew/class-interference
License: MIT
Author: Artem Novikov
Author-email: artnew@list.ru
Requires-Python: >=3.8,<4.0
Classifier: License :: OSI Approved :: MIT License
Classifier: Programming Language :: Python :: 3
Classifier: Programming Language :: Python :: 3.8
Classifier: Programming Language :: Python :: 3.9
Classifier: Programming Language :: Python :: 3.10
Classifier: Programming Language :: Python :: 3.11
Classifier: Typing :: Typed
Project-URL: Repository, https://github.com/reartnew/class-interference
